writings/_init__.py
writings/writings.py
writings-0.1.3.dist-info/METADATA
writings-0.1.3.dist-info/WHEEL
writings-0.1.3.dist-info/top_level.txt
writings-0.1.3.dist-info/RECORD
