Metadata-Version: 2.4
Name: writings
Version: 0.1.3
Summary: A simple chatbot syle printing system
Author-email: Dorian Ben <doribenbass@gmail.com>
License: MIT
Requires-Python: >=3.7
